Metadata-Version: 1.0
Name: audio.psychoacoustics
Version: 1.0.3
Summary: Psychoacoustics
Home-page: UNKNOWN
Author: Sébastien Boisgérault
Author-email: Sebastien.Boisgerault@mines-paristech.fr
License: MIT License
Platform: UNKNOWN
